AlgoPlus/TORAStockV3x.cpython-37m-x86_64-linux-gnu.so
AlgoPlus/_AlgoPlusTORAStockV3x.so
AlgoPlus/__init__.py
AlgoPlus/libAlgoPlusTORAStockV3xPy37.so
AlgoPlus/libmdapi.so
AlgoPlus/libtraderapi.so
AlgoPlusTORAStockV3x-0.1.dist-info/METADATA
AlgoPlusTORAStockV3x-0.1.dist-info/RECORD
AlgoPlusTORAStockV3x-0.1.dist-info/WHEEL
AlgoPlusTORAStockV3x-0.1.dist-info/top_level.txt
